tno.euphorie-12.0.0-py3.12-nspkg.pth
tno/euphorie/__init__.py
tno/euphorie/configure.zcml
tno/euphorie/interfaces.py
tno/euphorie/model.py
tno/euphorie/schema.py
tno/euphorie/testing.py
tno/euphorie/assets/od-logo.png
tno/euphorie/client/__init__.py
tno/euphorie/client/client.py
tno/euphorie/client/configure.zcml
tno/euphorie/client/browser/__init__.py
tno/euphorie/client/browser/company.py
tno/euphorie/client/browser/configure.zcml
tno/euphorie/client/browser/docx_reports.py
tno/euphorie/client/browser/module.py
tno/euphorie/client/browser/report.py
tno/euphorie/client/browser/risk.py
tno/euphorie/client/browser/session.py
tno/euphorie/client/browser/overrides/euphorie.client.browser.templates.conditions-bare.pt
tno/euphorie/client/browser/templates/measures_overview.pt
tno/euphorie/client/browser/templates/report_company.pt
tno/euphorie/client/browser/templates/report_landing.pt
tno/euphorie/client/browser/templates/rie.docx
tno/euphorie/content/__init__.py
tno/euphorie/content/configure.zcml
tno/euphorie/content/browser/__init__.py
tno/euphorie/content/browser/configure.zcml
tno/euphorie/content/browser/survey.py
tno/euphorie/content/browser/templates/survey_view.pt
tno/euphorie/locales/nl/LC_MESSAGES/euphorie.po
tno/euphorie/nuplone/__init__.py
tno/euphorie/nuplone/configure.zcml
tno/euphorie/nuplone/interfaces.py
tno/euphorie/nuplone/widget.py
tno/euphorie/nuplone/templates/error_unauthorized.pt
tno/euphorie/nuplone/templates/largetextarea_input.pt
tno/euphorie/nuplone/templates/wysiwyg_input.pt
tno/euphorie/profiles/default/browserlayer.xml
tno/euphorie/profiles/default/mailhost.xml
tno/euphorie/profiles/default/metadata.xml
tno/euphorie/profiles/default/properties.xml
tno/euphorie/profiles/default/skins.xml
tno/euphorie/templates/upload.pt
tno/euphorie/tests/__init__.py
tno/euphorie/tests/test_company.py
tno/euphorie/tests/test_module.py
tno/euphorie/tests/test_report.py
tno/euphorie/tests/test_risk.py
tno/euphorie/tests/test_session.py
tno_euphorie-12.0.0.dist-info/METADATA
tno_euphorie-12.0.0.dist-info/WHEEL
tno_euphorie-12.0.0.dist-info/namespace_packages.txt
tno_euphorie-12.0.0.dist-info/top_level.txt
tno_euphorie-12.0.0.dist-info/RECORD
