Metadata-Version: 2.4
Name: tno.euphorie
Version: 12.0.0
Summary: TNO specific extensions for Euphorie
Home-page: http://readthedocs.org/docs/tnoeuphorie/en/latest/
Author: Wichert Akkerman and Syslab.com
Author-email: info@syslab.com
License: GPL
Keywords: Euphorie OIRA RIE
Classifier: Development Status :: 5 - Production/Stable
Classifier: Environment :: Web Environment
Classifier: Framework :: Plone
Classifier: Framework :: Plone :: 5.2
Classifier: Framework :: Plone :: 6.0
Classifier: License :: OSI Approved :: GNU General Public License (GPL)
Classifier: Natural Language :: Dutch
Classifier: Operating System :: OS Independent
Classifier: Programming Language :: Python :: 3 :: Only
Classifier: Programming Language :: Python :: 3.8
Classifier: Programming Language :: Python :: 3.9
Classifier: Programming Language :: Python :: 3.10
Classifier: Programming Language :: Python :: 3.11
Classifier: Topic :: Internet :: WWW/HTTP
Requires-Dist: Euphorie>=12.0.0
Requires-Dist: NuPlone>=2.0.0
Requires-Dist: Pillow
Requires-Dist: alembic
Requires-Dist: ftw.upgrade
Requires-Dist: Products.statusmessages
Requires-Dist: plone.autoform
Requires-Dist: plone.tiles
Requires-Dist: requests
Requires-Dist: setuptools
Requires-Dist: zope.publisher
Requires-Dist: plone.api
Requires-Dist: z3c.jbot
Provides-Extra: tests
Requires-Dist: Euphorie[tests]; extra == "tests"
Dynamic: author
Dynamic: author-email
Dynamic: classifier
Dynamic: description
Dynamic: home-page
Dynamic: keywords
Dynamic: license
Dynamic: provides-extra
Dynamic: requires-dist
Dynamic: summary
